livekit/plugins/lemonslice/__init__.py
livekit/plugins/lemonslice/api.py
livekit/plugins/lemonslice/avatar.py
livekit/plugins/lemonslice/log.py
livekit/plugins/lemonslice/py.typed
livekit/plugins/lemonslice/version.py
livekit_plugins_lemonslice-1.3.12rc1.dist-info/METADATA
livekit_plugins_lemonslice-1.3.12rc1.dist-info/WHEEL
livekit_plugins_lemonslice-1.3.12rc1.dist-info/RECORD
