Metadata-Version: 2.4
Name: livekit-plugins-lemonslice
Version: 1.3.12rc1
Summary: Agent Framework plugin for LemonSlice
Project-URL: Documentation, https://docs.livekit.io
Project-URL: Source, https://github.com/livekit/agents
Project-URL: Website, https://livekit.io/
Author-email: LiveKit <support@livekit.io>
License-Expression: Apache-2.0
Keywords: agent,ai,audio,avatar,lemonslice,livekit,realtime,video,voice,webrtc
Classifier: Intended Audience :: Developers
Classifier: License :: OSI Approved :: Apache Software License
Classifier: Programming Language :: Python :: 3
Classifier: Programming Language :: Python :: 3 :: Only
Classifier: Programming Language :: Python :: 3.9
Classifier: Programming Language :: Python :: 3.10
Classifier: Topic :: Multimedia :: Sound/Audio
Classifier: Topic :: Multimedia :: Video
Classifier: Topic :: Scientific/Engineering :: Artificial Intelligence
Requires-Python: >=3.9.0
Requires-Dist: livekit-agents>=1.4.0.rc2
